driveui/__init__.py
driveui/static/driveui/favicon.svg
driveui/static/driveui/css/driveui.css
driveui/static/driveui/css/driveui.css.map
driveui/static/driveui/fonts/test-drive-nissan.eot
driveui/static/driveui/fonts/test-drive-nissan.svg
driveui/static/driveui/fonts/test-drive-nissan.ttf
driveui/static/driveui/fonts/test-drive-nissan.woff
driveui/static/driveui/icons/icons.css
driveui/static/driveui/images/hero-img.png
driveui/static/driveui/images/logo.svg
driveui-0.0.1.dist-info/METADATA
driveui-0.0.1.dist-info/WHEEL
driveui-0.0.1.dist-info/top_level.txt
driveui-0.0.1.dist-info/RECORD
